conf/datastore.default.yml
conf/logging.default.yml
docker/luna_tutorial/docker-compose.yml
docker/luna_tutorial/vmount/provision.py
docker/luna_tutorial/vmount/classifier/__init__.py
docker/luna_tutorial/vmount/classifier/analyze.py
docker/luna_tutorial/vmount/classifier/data.py
docker/luna_tutorial/vmount/classifier/losses.py
docker/luna_tutorial/vmount/classifier/model.py
docker/luna_tutorial/vmount/classifier/utils.py
docker/luna_tutorial/vmount/conf/app_config.yaml
docker/luna_tutorial/vmount/conf/collect_tiles.yaml
docker/luna_tutorial/vmount/conf/dsa_app_config.yaml
docker/luna_tutorial/vmount/conf/dsa_point_annotation.yaml
docker/luna_tutorial/vmount/conf/dsa_regional_annotation.yaml
docker/luna_tutorial/vmount/conf/generate_tiles.yaml
docker/luna_tutorial/vmount/conf/generate_tiles_all_tissues.yaml
docker/luna_tutorial/vmount/conf/infer_tiles.yaml
docker/luna_tutorial/vmount/conf/load_slides.yaml
docker/luna_tutorial/vmount/conf/manifest.yaml
docker/luna_tutorial/vmount/conf/regional_annotation_config.yaml
docker/luna_tutorial/vmount/conf/visualize_tiles.yaml
docker/luna_tutorial/vmount/conf/wsi_config.yaml
docker/luna_tutorial/vmount/conf/snakemake-configs/app_config.yaml
docker/luna_tutorial/vmount/conf/snakemake-configs/collect_tiles.yaml
docker/luna_tutorial/vmount/conf/snakemake-configs/generate_tiles_test.yaml
docker/luna_tutorial/vmount/conf/snakemake-configs/generate_tiles_train.yaml
docker/luna_tutorial/vmount/conf/snakemake-configs/infer_tiles.yaml
docker/luna_tutorial/vmount/conf/snakemake-configs/load_slides.yaml
docker/luna_tutorial/vmount/conf/snakemake-configs/regional_annotation_config.yaml
docker/luna_tutorial/vmount/conf/snakemake-configs/visualize_tiles.yaml
docker/luna_tutorial/vmount/conf/snakemake-configs/wsi_config.yaml
docker/luna_tutorial/vmount/conf/snakemake-configs/scripts/collect_tiles_train.py
docker/luna_tutorial/vmount/conf/snakemake-configs/scripts/generate_tiles_train.py
pyluna-0.3.3.dist-info/LICENSE
pyluna-0.3.3.dist-info/METADATA
pyluna-0.3.3.dist-info/WHEEL
pyluna-0.3.3.dist-info/top_level.txt
pyluna-0.3.3.dist-info/zip-safe
pyluna-0.3.3.dist-info/RECORD
