Metadata-Version: 2.1
Name: pyluna
Version: 0.3.3
Summary: Transformation functions and services for multi-modal oncology data
Home-page: https://componcmsk.org/msk-mind/
Author: msk-mind
Author-email: CompOncBST@mskcc.org
License: Apache License version 2.0
Project-URL: Bug Tracker, https://github.com/msk-mind/luna/issues
Keywords: radiology,pathology,clinical
Platform: UNKNOWN
Classifier: Framework :: Pytest
Classifier: Development Status :: 3 - Alpha
Classifier: License :: OSI Approved :: Apache Software License
Classifier: Operating System :: OS Independent
Classifier: Programming Language :: Python :: 3
Classifier: Programming Language :: Python :: 3.6
Classifier: Programming Language :: Python :: 3.7
Classifier: Topic :: Scientific/Engineering :: Artificial Intelligence
License-File: LICENSE
Requires-Dist: pyluna-core
Provides-Extra: all
Requires-Dist: pyluna-radiology ; extra == 'all'
Requires-Dist: pyluna-pathology ; extra == 'all'
Provides-Extra: dev
Requires-Dist: pyluna-radiology ; extra == 'dev'
Requires-Dist: pyluna-pathology ; extra == 'dev'
Requires-Dist: pytest ; extra == 'dev'
Requires-Dist: pytest-cov ; extra == 'dev'
Requires-Dist: pytest-mock ; extra == 'dev'
Requires-Dist: pytest-runner ; extra == 'dev'
Requires-Dist: testfixtures ; extra == 'dev'
Requires-Dist: requests-mock ; extra == 'dev'
Requires-Dist: mock ; extra == 'dev'
Requires-Dist: wheel (>=0.22) ; extra == 'dev'
Requires-Dist: pyinstaller (>=4.0) ; extra == 'dev'
Requires-Dist: poetry ; extra == 'dev'
Requires-Dist: python-semantic-release ; extra == 'dev'
Requires-Dist: m2r2 ; extra == 'dev'
Requires-Dist: twine ; extra == 'dev'
Requires-Dist: Sphinx ; extra == 'dev'
Requires-Dist: sphinx-click ; extra == 'dev'
Requires-Dist: nbsphinx ; extra == 'dev'
Requires-Dist: ipython ; extra == 'dev'
Requires-Dist: pre-commit ; extra == 'dev'
Provides-Extra: pathology
Requires-Dist: pyluna-pathology ; extra == 'pathology'
Provides-Extra: radiology
Requires-Dist: pyluna-radiology ; extra == 'radiology'
